LICENSE.txt
MANIFEST.in
README.md
paired.py
setup.cfg
setup.py
paired.egg-info/PKG-INFO
paired.egg-info/SOURCES.txt
paired.egg-info/dependency_links.txt
paired.egg-info/top_level.txt