Metadata-Version: 2.1
Name: paired
Version: 0.0.1
Summary: Sequence alignment of Python objects.
Home-page: https://github.com/ajnisbet/paired
Author: Andrew Nisbet
License: MIT
Project-URL: Documentation, https://github.com/ajnisbet/paired
Project-URL: Source, https://github.com/ajnisbet/paired
Platform: UNKNOWN
Classifier: License :: OSI Approved :: MIT License
Classifier: Operating System :: OS Independent
Classifier: Programming Language :: Python
Classifier: Programming Language :: Python :: 2
Classifier: Programming Language :: Python :: 3
Classifier: Programming Language :: Python :: Implementation :: CPython
